surquest/utils/split_balancer/__init__.py
surquest/utils/split_balancer/errors.py
surquest/utils/split_balancer/split_balancer.py
surquest_split_balancer-0.0.6.dist-info/METADATA
surquest_split_balancer-0.0.6.dist-info/WHEEL
surquest_split_balancer-0.0.6.dist-info/licenses/LICENSE
surquest_split_balancer-0.0.6.dist-info/RECORD
