Metadata-Version: 2.3
Name: surquest-split-balancer
Version: 0.0.6
Summary: A Python package for dividing a set of units into two most comparable groups based on their characteristics.
Project-URL: Homepage, https://github.com/surquest/python-split-balancer
Project-URL: Bug Tracker, https://github.com/surquest/python-split-balancer/issues
Author-email: Michal Švarc <michal.svarc@surquest.com>
License-File: LICENSE
Requires-Dist: ortools>=9.9.3963
Requires-Dist: requests
Provides-Extra: test
Requires-Dist: pytest-cov>=5.0.0; extra == 'test'
Requires-Dist: pytest>=8.1.1; extra == 'test'
